gjt/__init__.py
gjt/account/__init__.py
gjt/account/login_to_account.py
gjt/castle/buildings.py
gjt/castle/recruit_troops.py
gjt/map/__init__.py
gjt/map/attacking.py
gjt/map/switch_kingdoms.py
gjt/misc/__init__.py
gjt/misc/connect_to_websocket.py
gjt/misc/get_error_data.py
gjt/misc/get_network_data.py
gjt/misc/skips_calculator.py
gjt/utils/ask_prompts.py
gjt/utils/settings.py
gjt-2.2.10.dist-info/licenses/LICENSE
gjt-2.2.10.dist-info/METADATA
gjt-2.2.10.dist-info/WHEEL
gjt-2.2.10.dist-info/top_level.txt
gjt-2.2.10.dist-info/RECORD
