Metadata-Version: 2.4
Name: gjt
Version: 2.2.10
Summary: Python library to interact with Goodgame Empire websocket server.
Author-email: SasakiTeam <wojts8@proton.me>
License-Expression: MIT
Project-URL: Homepage, https://github.com/wojts8/gjt/
Requires-Python: >=3.12
License-File: LICENSE
Requires-Dist: websockets
Requires-Dist: requests
Requires-Dist: packaging
Dynamic: license-file
